<?xml version="1.0" encoding="utf-8" ?><dwsync><file name="new_install_coupon.jpg" local="-4256338772456636416" remote="-4256338769235428440" testing="0" /><file name="duct_clean_coupon.jpg" local="-4256338772456636416" remote="-4256338769235428440" testing="0" /><file name="parts_coupon.jpg" local="-4256338772456636416" remote="-4256338769235428440" testing="0" /><file name="december_coupon.jpg" local="-4256338772456636416" remote="-4256338769235428440" testing="0" /><file name="december_coupon.png" local="-4256338772456636416" remote="-4256338769235428440" testing="0" /><file name="duct_clean_coupon.png" local="-4256338772456636416" remote="-4256338769235428440" testing="0" /><file name="new_install_coupon.png" local="-4256338772456636416" remote="-4256338769235428440" testing="0" /><file name="parts_coupon.png" local="-4256338772456636416" remote="-4256338769235428440" testing="0" /><file name="res_header.swf" local="-4256338772456636416" remote="-4256338769235428440" testing="0" /><file name="res_header.swi" local="-4256338772456636416" remote="-4256338769235428440" testing="0" /><file name="march09.jpg" local="-4186574759674249216" remote="-4186574756453041240" testing="0" /><file name="coupon.pdf" local="-4048576429661618176" remote="-4048576429661618176" testing="0" /><file name="may09.jpg" local="-4168391586129903616" remote="-4168391582908695640" testing="0" /></dwsync>